[
    {
    "soal": "ุงูู ูู ููุชุจ ูุนูู ุงูุงูููุฌู ูููุฒ โฆ ๐ ",
    "jawaban": "ูุญูู"
  },
  {
    "soal": "ุงูู ูู ููุชุจ ูุนูู ุงูุงูููุฌู ูููุฒ โฆ ๐",
    "jawaban": "ุจุงุต"
  },
  {
    "soal": "ุงูู ูู ููุชุจ ูุนูู ุงูุงูููุฌู ูููุฒ โฆ ๐ก๏ธ",
    "jawaban": "ุฏุฑุน"
  },
  {
    "soal": "ุงูู ูู ููุชุจ ูุนูู ุงูุงูููุฌู ูููุฒ โฆ ๐",
    "jawaban": "ุงุจุฑู"
  },
  {
    "soal": "ุงูู ูู ููุชุจ ูุนูู ุงูุงูููุฌู ูููุฒ โฆ ๐ง",
    "jawaban": "ุณูุงุนู"
  },
  {
    "soal": "ุงูู ูู ููุชุจ ูุนูู ุงูุงูููุฌู ูููุฒ โฆ ๐ฆ",
    "jawaban": "ุฏูู ุฑููู"
  },
  {
    "soal": "ุงูู ูู ููุชุจ ูุนูู ุงูุงูููุฌู ูููุฒ โฆ ๐ฆ",
    "jawaban": "ูุตุจุงุญ"
  },
  {
    "soal": "ุงูู ูู ููุชุจ ูุนูู ุงูุงูููุฌู ูููุฒ โฆ ๐ฅ",
    "jawaban": "ูุงุฑ"
   },
  {
    "soal": "ุงูู ูู ููุชุจ ูุนูู ุงูุงูููุฌู ูููุฒ โฆ ๐ต",
    "jawaban": "ุตุจุงุฑ"
    },
  {
    "soal": "ุงูู ูู ููุชุจ ูุนูู ุงูุงูููุฌู ูููุฒ โฆ ๐ก",
    "jawaban": "ููุจู"   
   },
  {
    "soal": "ุงูู ูู ููุชุจ ูุนูู ุงูุงูููุฌู ูููุฒ โฆ โฐ๏ธ",
    "jawaban": "ุชุงุจูุช"     
  }
]
